pypalexcpptest/__init__.py
pypalexcpptest/__main__.py
pypalexcpptest/arg_messages.py
pypalexcpptest/conversion_tests.py
pypalexcpptest/conversion_utils.py
pypalexcpptest/image_utils.py
pypalexcpptest/settings.py
pypalexcpptest-0.0.2.dist-info/LICENSE
pypalexcpptest-0.0.2.dist-info/METADATA
pypalexcpptest-0.0.2.dist-info/WHEEL
pypalexcpptest-0.0.2.dist-info/entry_points.txt
pypalexcpptest-0.0.2.dist-info/top_level.txt
pypalexcpptest-0.0.2.dist-info/RECORD
